{
  "_id": "US/MO-Legislation/322.030",
  "_source": "US/MO-Legislation",
  "_type": "legislation",
  "_fetched_at": "2026-04-18T23:38:31.579577+00:00",
  "title": "Missouri Revised Statutes § 322.030 - Duty of owner or person in charge to kill dog or have immunized",
  "text": "322.030.  Duty of owner or person in charge to kill dog or have immunized. — Whenever any dog has been bitten by, fought with, or has been substantially exposed to any dog affected with rabies, it shall be the duty of the owner, or person in charge thereof, forthwith to kill such exposed dog or have it immunized against rabies at the owner's or custodian's expense, by the administration of antirabic virus by a licensed veterinarian.\n(RSMo 1939 § 14540, repealed L. 1953 p. 662 § A, again enacted L. 1955 p. 754) \nPrior revision: 1929 § 12866",
  "date": "2025-01-01",
  "url": "https://revisor.mo.gov/main/OneSection.aspx?section=322.030",
  "section_id": "322.030",
  "chapter": "322",
  "jurisdiction": "US-MO",
  "language": "en"
}