{
  "_id": "US/MO-Legislation/375.1087",
  "_source": "US/MO-Legislation",
  "_type": "legislation",
  "_fetched_at": "2026-04-19T00:52:45.632309+00:00",
  "title": "Missouri Revised Statutes § 375.1087 - Contributions to guaranty fund prohibited — guaranty fund to cover only specified risks",
  "text": "375.1087.  Contributions to guaranty fund prohibited — guaranty fund to cover only specified risks. — 1.  No risk retention group shall be required or permitted to join or contribute financially to any insurance insolvency guaranty fund, or similar mechanism, in this state, nor shall any risk retention group, or its insureds or claimants against its insureds, receive any benefit from any such fund for claims arising under the insurance policies issued by such risk retention group.\n  2.  When a purchasing group obtains insurance covering its members' risks from an insurer not authorized in this state or a risk retention group, no such risks, wherever resident or located, shall be covered by any insurance guaranty fund or similar mechanism in this state.\n  3.  When a purchasing group obtains insurance covering its members' risks from an authorized insurer, only risks resident or located in this state shall be covered by any applicable state guaranty funds.\n  4.  The director may require or exempt a risk retention group from participation in any mechanism established or authorized under the laws of this state for the equitable apportionment among insurers of liability insurance losses and expenses incurred on policies written through such mechanism, and such risk retention group shall submit sufficient information to the director to enable the director to apportion on a nondiscriminatory basis the risk retention group's proportionate share of such losses and expenses.\n(L. 1991 H.B. 385, et al. § 28)",
  "date": "2025-01-01",
  "url": "https://revisor.mo.gov/main/OneSection.aspx?section=375.1087",
  "section_id": "375.1087",
  "chapter": "375",
  "jurisdiction": "US-MO",
  "language": "en"
}