{
  "_id": "US/MO-Legislation/9.115",
  "_source": "US/MO-Legislation",
  "_type": "legislation",
  "_fetched_at": "2026-04-18T17:17:17.522310+00:00",
  "title": "Missouri Revised Statutes § 9.115 - Patriots Day, April 19 — how observed",
  "text": "9.115.  Patriots Day, April 19 — how observed. — April nineteenth of every year shall be known and designated as \"Patriots Day\".  It shall be a day on which to commemorate the day of the \"shot heard 'round the world\" and the beginning of the American Revolution.  The teachers and students of the schools of this state shall observe the day with appropriate exercises.  All citizens of this state are requested to devote some portion of patriots day to solemn contemplation on the selfless sacrifice made by those who fought and gave their lives for our nation's independence.\n(L. 2002 H.B. 1519)",
  "date": "2025-01-01",
  "url": "https://revisor.mo.gov/main/OneSection.aspx?section=9.115",
  "section_id": "9.115",
  "chapter": "9",
  "jurisdiction": "US-MO",
  "language": "en"
}